{
  "env": "development",

  "envUrl": {
    "elementBaseUrl": "http://172.20.10.9:7091",
    "orderBaseUrl": "http://172.20.10.9:8094",
    "bossWebBaseUrl":"https://test.huarunbao.com/api/boss-web-p",
    "filePicUrl": "https://test.huarunbao.com/crib-file",
    "interface":"https://test.huarunbao.com/interface",
    "baseUrl": "https://test.huarunbao.com/crib-app-vue/p",
    "productShare": "https://test.huarunbao.com/crib-app-vue/p/insurance?share=copyUrl",
    "cribVueUrl": "https://test.huarunbao.com/crib-prod-vue/p",
    "priceBase": 30000,
    "pageUrl": "/userInfo/loginRisk",
    "gasMainUrl": "/user/productList",
    "insuranceMainUrl": "/insurance",
    "houseInsuranceMainUrl": "/houseInsurance",
    "gasOrderDetailInfoUrl": "/user/orderListGas?status=1&tabStatus=0",
    "insuranceOrderDetailInfoUrl": "/user/orderListRisk?tabStatus=0",
    "tenantsPolicyUrl": "https://test.huarunbao.com/crib-app-vue/p/tenantmanage/tenantPolicyList?memberId=",
    "newTenantsPolicyUrl": "https://test.huarunbao.com/crib-app-vue/p/tenantmanageNew/tenantPolicyList?memberId=",
    "tenantsInsuredMainUrl": "/tenantsInsur?sign=",
    "newTenantsInsuredMainUrl": "/newTenantsInsur?sign=",
    "tenantsWechat": "18665863292",
    "tenantsEmail": "liwenying41@crc.com.hk",
    "activityUrl": "/activity/luckyDraw?orderNo=",
    "openSign": true,
    "payUrl": "https://test.huarunbao.com/crib-pay-vue",
    "crbBank": {
      "apiJs": "https://epay.uat.crbank.com.cn:478/mbanking/scripts/open/jcrb-1.0.0.js"
    },
    "jsUrl": "https://test.huarunbao.com",
    "emallHomeUrl": "https://sit-emall-h5.huarunbao.com",
    "emallPolicyUrl": "https://sit-emall-h5.huarunbao.com/me/policy/list"
  },
  "externalChannel": [
    "16"
  ],
  "newExternalChannel": [
    "20", "1", "23"
  ],
  "externalChannelUrl":{
    "fanya": {
      "orderInfoUrl": "https://mqa.eshebao.cn/commercialInsuranceToOrder.html",
      "channelCode": "16"
    }
  }
}
